entropypass/__init__.py
entropypass/cli.py
entropypass/password_gen.py
entropypass-1.0.0.dist-info/LICENSE
entropypass-1.0.0.dist-info/METADATA
entropypass-1.0.0.dist-info/WHEEL
entropypass-1.0.0.dist-info/entry_points.txt
entropypass-1.0.0.dist-info/top_level.txt
entropypass-1.0.0.dist-info/RECORD
