Metadata-Version: 2.1
Name: entropypass
Version: 1.0.0
Summary: A Python-based tool to generate high-entropy passwords using Leet substitutions and entropy optimization.
Home-page: https://github.com/Tcookie47/entropypass
Author: Anantha Krishna Anumanchipalli
Author-email: anumanchipalli.a@northeastern.edu
License: UNKNOWN
Platform: UNKNOWN
Classifier: Programming Language :: Python :: 3
Classifier: License :: OSI Approved :: MIT License
Classifier: Operating System :: OS Independent
Requires-Python: >=3.6
License-File: LICENSE
